ecs_metadata/__init__.py
ecs_metadata/main.py
ecs_metadata-0.1.0.dist-info/LICENSE
ecs_metadata-0.1.0.dist-info/WHEEL
ecs_metadata-0.1.0.dist-info/METADATA
ecs_metadata-0.1.0.dist-info/RECORD
