Metadata-Version: 2.1
Name: ecs-metadata
Version: 0.1.0
Summary: Get the meta data of the current ECS container, or empty variables if outside of ECS.
License: MIT
Author: Paris Kasidiaris
Author-email: paris@kasidiaris.com
Requires-Python: >=3.8,<4.0
Classifier: License :: OSI Approved :: MIT License
Classifier: Programming Language :: Python :: 3
Classifier: Programming Language :: Python :: 3.8
Classifier: Programming Language :: Python :: 3.9
Requires-Dist: requests (>=2.25.1,<3.0.0)
